modelbase_migrate/__init__.py
modelbase_migrate/types.py
modelbase_migrate-0.1.0.dist-info/METADATA
modelbase_migrate-0.1.0.dist-info/WHEEL
modelbase_migrate-0.1.0.dist-info/RECORD
